{
    "n01532829": "Purple finch",
    "n01558993": "Bird",
    "n01704323": "Dinosaur",
    "n01749939": "Viper",
    "n01770081": "Spider",
    "n01855672": "Goose",
    "n01910747": "Jellyfish",
    "n01981276": "Lobster",
    "n02074367": "manatees(sea cow)",
    "n02089867": "American Foxhound",
    "n02091831": "Persian Greyhound",
    "n02099601": "Golden Retrievers",
    "n02101006": "Gordon Setter",
    "n02108551": "Tibetan Mastiff",
    "n02110063": "Alaskan Malamute",
    "n02110341": "Dalmatian",
    "n02111277": "NewFoundLand",
    "n02113712": "Poodle",
    "n02116738": "African Wild Dog",
    "n02120079": "Arctic Fox",
    "n02129165": "Lion",
    "n02138441": "Meerkat",
    "n02165456": "Ladybug",
    "n02174001": "Beetle",
    "n02219486": "Ant",
    "n02457408": "Sloth",
    "n02606052": "Angelfish",
    "n02823428": "Beer bottle",
    "n02871525": "Bookstore",
    "n02966193": "Carousel",
    "n03047690": "Footwear",
    "n03146219": "Armor",
    "n03207743": "dishcloth",
    "n03220513": "Dome",
    "n03272010": "Guitar",
    "n03337140": "Shelf",
    "n03347037": "Furnace",
    "n03400231": "Cooking pan",
    "n03417042": "Garbage Truck",
    "n03476684": "hair barrettes",
    "n03527444": "gun holster",
    "n03535780": "Gymnast",
    "n03544143": "Hourglass",
    "n03676483": "Lipstick",
    "n03773504": "Missile",
    "n03775546": "Coffee cup",
    "n03838899": "Trumpet",
    "n03854065": "organ, pipe organ",
    "n03888605": "gymnastics",
    "n03908618": "Pouch",
    "n03980874": "poncho (clothing)",
    "n03998194": "prayer mat",
    "n04067472": "fishing reels",
    "n04146614": "school bus",
    "n04149813": "scoreboard",
    "n04243546": "slot machine",
    "n04258138": "solar panel",
    "n04275548": "spider web",
    "n04296562": "concert",
    "n04389033": "army tanker",
    "n04418357": "stage",
    "n04443257": "Drugstore",
    "n04509417": "Unicycle",
    "n04515003": "Piano",
    "n04522168": "Artifact",
    "n04596742": "wok",
    "n06794110": "signboard",
    "n07613480": "cheesecake",
    "n07697537": "sausage",
    "n13133613": "corn"

}
